{"type":"FeatureCollection","totalFeatures":15,"features":[{"type":"Feature","id":"tram do am chinh1.1","geometry":{"type":"Point","coordinates":[103.09,22.03]},"geometry_name":"geom","properties":{"tentram":"Lai Châu","tinh":"Lai Châu","doam1":80,"doam2":79,"doam3":74,"doam4":76,"doam5":78,"doam6":88,"doam7":88,"doam8":90,"doam9":83,"doam10":79,"doam11":79,"doam12":82}},{"type":"Feature","id":"tram do am chinh1.2","geometry":{"type":"Point","coordinates":[103.54,21.2]},"geometry_name":"geom","properties":{"tentram":"Sơn La","tinh":"Sơn La","doam1":82,"doam2":77,"doam3":71,"doam4":68,"doam5":90,"doam6":87,"doam7":87,"doam8":89,"doam9":83,"doam10":80,"doam11":79,"doam12":77}},{"type":"Feature","id":"tram do am chinh1.3","geometry":{"type":"Point","coordinates":[105.13,21.49]},"geometry_name":"geom","properties":{"tentram":"Tuyên Quang","tinh":"Tuyên Quang","doam1":81,"doam2":82,"doam3":82,"doam4":86,"doam5":91,"doam6":82,"doam7":84,"doam8":86,"doam9":83,"doam10":76,"doam11":79,"doam12":75}},{"type":"Feature","id":"tram do am chinh1.4","geometry":{"type":"Point","coordinates":[105.51,21.01]},"geometry_name":"geom","properties":{"tentram":"Hà Nội","tinh":"Hà Nội","doam1":80,"doam2":80,"doam3":83,"doam4":87,"doam5":79,"doam6":79,"doam7":81,"doam8":85,"doam9":79,"doam10":72,"doam11":73,"doam12":71}},{"type":"Feature","id":"tram do am chinh1.5","geometry":{"type":"Point","coordinates":[107.04,20.57]},"geometry_name":"geom","properties":{"tentram":"Hồng Gai","tinh":"Quảng Ning","doam1":86,"doam2":84,"doam3":83,"doam4":85,"doam5":81,"doam6":86,"doam7":87,"doam8":88,"doam9":80,"doam10":70,"doam11":73,"doam12":74}},{"type":"Feature","id":"tram do am chinh1.6","geometry":{"type":"Point","coordinates":[106.1,20.26]},"geometry_name":"geom","properties":{"tentram":"Nam Định","tinh":"Nam Định","doam1":88,"doam2":88,"doam3":89,"doam4":92,"doam5":86,"doam6":84,"doam7":82,"doam8":87,"doam9":85,"doam10":80,"doam11":81,"doam12":81}},{"type":"Feature","id":"tram do am chinh1.7","geometry":{"type":"Point","coordinates":[105.4,18.4]},"geometry_name":"geom","properties":{"tentram":"Vinh","tinh":"Nghệ An","doam1":92,"doam2":91,"doam3":91,"doam4":90,"doam5":83,"doam6":75,"doam7":75,"doam8":81,"doam9":88,"doam10":87,"doam11":86,"doam12":71}},{"type":"Feature","id":"tram do am chinh1.8","geometry":{"type":"Point","coordinates":[107.41,16.24]},"geometry_name":"geom","properties":{"tentram":"Huế","tinh":"Thừa Thiên Huế","doam1":89,"doam2":91,"doam3":92,"doam4":85,"doam5":81,"doam6":77,"doam7":77,"doam8":80,"doam9":87,"doam10":89,"doam11":92,"doam12":92}},{"type":"Feature","id":"tram do am chinh1.9","geometry":{"type":"Point","coordinates":[108.11,16.02]},"geometry_name":"geom","properties":{"tentram":"Đà Nẵng","tinh":"Đà Nẵng","doam1":81,"doam2":86,"doam3":86,"doam4":86,"doam5":82,"doam6":78,"doam7":80,"doam8":81,"doam9":86,"doam10":87,"doam11":88,"doam12":84}},{"type":"Feature","id":"tram do am chinh1.10","geometry":{"type":"Point","coordinates":[109.43,13.46]},"geometry_name":"geom","properties":{"tentram":"Quy Nhơn","tinh":"Bình Định","doam1":78,"doam2":81,"doam3":83,"doam4":81,"doam5":78,"doam6":76,"doam7":76,"doam8":77,"doam9":82,"doam10":84,"doam11":81,"doam12":83}},{"type":"Feature","id":"tram do am chinh1.11","geometry":{"type":"Point","coordinates":[108,13.56]},"geometry_name":"geom","properties":{"tentram":"Plây Ku","tinh":"Gia Lai","doam1":79,"doam2":75,"doam3":72,"doam4":71,"doam5":81,"doam6":89,"doam7":93,"doam8":92,"doam9":93,"doam10":89,"doam11":87,"doam12":77}},{"type":"Feature","id":"tram do am chinh1.12","geometry":{"type":"Point","coordinates":[108.26,11.57]},"geometry_name":"geom","properties":{"tentram":"Đà Lạt","tinh":"Lâm Đồng","doam1":85,"doam2":78,"doam3":78,"doam4":81,"doam5":86,"doam6":84,"doam7":90,"doam8":91,"doam9":91,"doam10":89,"doam11":86,"doam12":86}},{"type":"Feature","id":"tram do am chinh1.13","geometry":{"type":"Point","coordinates":[109.12,12.15]},"geometry_name":"geom","properties":{"tentram":"Nha Trang","tinh":"Khánh Hòa","doam1":73,"doam2":81,"doam3":82,"doam4":80,"doam5":80,"doam6":78,"doam7":81,"doam8":81,"doam9":86,"doam10":86,"doam11":83,"doam12":82}},{"type":"Feature","id":"tram do am chinh1.14","geometry":{"type":"Point","coordinates":[106.4,10.49]},"geometry_name":"geom","properties":{"tentram":"TP. Hồ Chí Minh","tinh":"TP. Hồ Chí Minh","doam1":74,"doam2":70,"doam3":68,"doam4":75,"doam5":80,"doam6":84,"doam7":83,"doam8":81,"doam9":84,"doam10":82,"doam11":76,"doam12":75}},{"type":"Feature","id":"tram do am chinh1.15","geometry":{"type":"Point","coordinates":[105.1,9.1]},"geometry_name":"geom","properties":{"tentram":"Cà Mau","tinh":"Cà Mau","doam1":81,"doam2":79,"doam3":77,"doam4":78,"doam5":89,"doam6":88,"doam7":89,"doam8":89,"doam9":91,"doam10":85,"doam11":83,"doam12":82}}],"crs":{"type":"name","properties":{"name":"urn:ogc:def:crs:EPSG::4326"}}}