{"type":"FeatureCollection","totalFeatures":7,"features":[{"type":"Feature","id":"vn_vung_ts_2005.1","geometry":{"type":"Point","coordinates":[104.55675539524822,19.201286149536998]},"geometry_name":"geom","properties":{"t_vung":"Bắc Trung Bộ","ma_vung":3,"sl_2005":182210}},{"type":"Feature","id":"vn_vung_ts_2005.2","geometry":{"type":"Point","coordinates":[105.21232178348951,10.275405960136998]},"geometry_name":"geom","properties":{"t_vung":"Đồng bằng sông Cửu Long","ma_vung":6,"sl_2005":843017}},{"type":"Feature","id":"vn_vung_ts_2005.3","geometry":{"type":"Point","coordinates":[105.8142870312532,20.94197800122262]},"geometry_name":"geom","properties":{"t_vung":"Đồng bằng sông Hồng","ma_vung":1,"sl_2005":109273}},{"type":"Feature","id":"vn_vung_ts_2005.4","geometry":{"type":"Point","coordinates":[106.30969050896196,11.455915877294142]},"geometry_name":"geom","properties":{"t_vung":"Đông Nam Bộ","ma_vung":5,"sl_2005":232628}},{"type":"Feature","id":"vn_vung_ts_2005.5","geometry":{"type":"Point","coordinates":[107.87827591079713,15.597237101370563]},"geometry_name":"geom","properties":{"t_vung":"Duyên hải Nam Trung Bộ","ma_vung":7,"sl_2005":574932}},{"type":"Feature","id":"vn_vung_ts_2005.6","geometry":{"type":"Point","coordinates":[107.8471368636342,13.593100068299405]},"geometry_name":"geom","properties":{"t_vung":"Tây Nguyên","ma_vung":4,"sl_2005":3237}},{"type":"Feature","id":"vn_vung_ts_2005.7","geometry":{"type":"Point","coordinates":[104.6297299571459,22.223311040161697]},"geometry_name":"geom","properties":{"t_vung":"Trung du và miền núi Bắc Bộ","ma_vung":2,"sl_2005":42639}}],"crs":{"type":"name","properties":{"name":"urn:ogc:def:crs:EPSG::4326"}}}